{"27976": {"name": "Connext Network", "symbol": "NEXT", "date_added": "2023-09-06T03:47:49.000Z", "market_cap": 0, "volume": 22561557.21551852, "price": 0.06550473953985164, "volume_converted": "22.6M", "days_passed": 3, "hot": "yes", "old_price": 0.06611251353435237, "price_change": 0.9908069749279019}, "27992": {"name": "DORK LORD", "symbol": "DORKL", "date_added": "2023-09-07T09:43:05.000Z", "market_cap": 0, "volume": 14777726.41513935, "price": 0.004169426311459186, "volume_converted": "14.8M", "days_passed": 2, "hot": "yes", "old_price": 0.004918490687776054, "price_change": 0.8477044231925617}, "27922": {"name": "Shiba Saga", "symbol": "SHIA", "date_added": "2023-08-25T03:05:39.000Z", "market_cap": 0, "volume": 3892889.28830041, "price": 0.14433819011873175, "volume_converted": "3.9M", "days_passed": 15, "hot": "no", "old_price": 0.14974556835416214, "price_change": 0.9638895608406826}, "27928": {"name": "Pepe Community", "symbol": "PEPE", "date_added": "2023-08-27T03:21:38.000Z", "market_cap": 0, "volume": 3620937.6941922, "price": 0.003252450322164386, "volume_converted": "3.6M", "days_passed": 13, "hot": "no", "old_price": 0.0033564596063323593, "price_change": 0.9690122044157041}, "27963": {"name": "Shiba V Pepe", "symbol": "SHEPE", "date_added": "2023-09-01T15:49:02.000Z", "market_cap": 0, "volume": 2908553.76092818, "price": 2.686577108759074e-09, "volume_converted": "2.9M", "days_passed": 8, "hot": "no", "old_price": 3.118363492528146e-09, "price_change": 0.8615343000251038}, "27935": {"name": "PEPECASH", "symbol": "PEPECASH", "date_added": "2023-08-28T09:54:01.000Z", "market_cap": 0, "volume": 2575642.22287161, "price": 3.626211252094526e-05, "volume_converted": "2.6M", "days_passed": 12, "hot": "no", "old_price": 3.631289572080004e-05, "price_change": 0.9986015105970826}, "27862": {"name": "Veloce", "symbol": "VEXT", "date_added": "2023-09-04T10:04:03.000Z", "market_cap": 12269161.517769707, "volume": 1756095.77619323, "price": 0.5543547465874109, "volume_converted": "1.8M", "days_passed": 5, "hot": "no", "old_price": 0.5545762748357201, "price_change": 0.9996005450316553}, "26748": {"name": "Tidalflats", "symbol": "TIDE", "date_added": "2023-09-02T04:45:13.000Z", "market_cap": 0, "volume": 1586657.94042575, "price": 0.048798398153774784, "volume_converted": "1.6M", "days_passed": 7, "hot": "no", "old_price": 0.048926330654803646, "price_change": 0.9973852013973523}, "27920": {"name": "HarryPotterObamaInu", "symbol": "INU", "date_added": "2023-08-25T00:41:25.000Z", "market_cap": 0, "volume": 1228811.47818773, "price": 0.0007552641540876797, "volume_converted": "1.2M", "days_passed": 15, "hot": "no", "old_price": 0.0007633103310017224, "price_change": 0.9894588392332077}, "27997": {"name": "DORK LORD", "symbol": "DORKL", "date_added": "2023-09-08T10:05:22.000Z", "market_cap": 0, "volume": 550670.92410118, "price": 8.131757002643134e-05, "volume_converted": "550.0K", "days_passed": 1, "hot": "yes", "old_price": 0.00010020856280360365, "price_change": 0.8114832480514035}, "27924": {"name": "Ultimate Tipbot", "symbol": "ULTIMATEBOT", "date_added": "2023-08-25T09:12:25.000Z", "market_cap": 0, "volume": 409824.66185415, "price": 0.020991945553160488, "volume_converted": "409.0K", "days_passed": 15, "hot": "no", "old_price": 0.021023145983788672, "price_change": 0.998515900966856}, "27938": {"name": "Dejitaru Hoshi", "symbol": "HOSHI", "date_added": "2023-08-29T09:03:16.000Z", "market_cap": 0, "volume": 406348.52886694, "price": 0.004000859464417086, "volume_converted": "406.0K", "days_passed": 11, "hot": "no", "old_price": 0.003961812672794964, "price_change": 1.0098557894698679}}