{"27922": {"name": "Shiba Saga", "symbol": "SHIA", "date_added": "2023-08-25T03:05:39.000Z", "market_cap": 0, "volume": 7984463.40361754, "price": 0.26886415894129273, "volume_converted": "8.0M", "days_passed": 10, "hot": "no", "old_price": 0.2856262984140242, "price_change": 0.9413144393012641}, "27928": {"name": "Pepe Community", "symbol": "PEPE", "date_added": "2023-08-27T03:21:38.000Z", "market_cap": 0, "volume": 5690390.56365861, "price": 0.00598409819141789, "volume_converted": "5.7M", "days_passed": 8, "hot": "no", "old_price": 0.0061458412177683224, "price_change": 0.973682524390182}, "27963": {"name": "Shiba V Pepe", "symbol": "SHEPE", "date_added": "2023-09-01T15:49:02.000Z", "market_cap": 0, "volume": 3418263.38398404, "price": 1.642722137008342e-08, "volume_converted": "3.4M", "days_passed": 3, "hot": "yes", "old_price": 1.6924295014337248e-08, "price_change": 0.9706295805034871}, "27926": {"name": "Xccelerate", "symbol": "XLRT", "date_added": "2023-08-29T08:19:41.000Z", "market_cap": 0, "volume": 2927838.30284513, "price": 0.0050355913455175545, "volume_converted": "2.9M", "days_passed": 6, "hot": "no", "old_price": 0.005377062107927481, "price_change": 0.9364949194270061}, "27901": {"name": "shares.finance", "symbol": "SHARES", "date_added": "2023-08-23T02:42:23.000Z", "market_cap": 0, "volume": 1649732.92680913, "price": 10.282181950123096, "volume_converted": "1.6M", "days_passed": 12, "hot": "no", "old_price": 9.341293688145212, "price_change": 1.1007235500123436}, "27920": {"name": "HarryPotterObamaInu", "symbol": "INU", "date_added": "2023-08-25T00:41:25.000Z", "market_cap": 0, "volume": 1232602.04956483, "price": 0.0006303842853117618, "volume_converted": "1.2M", "days_passed": 10, "hot": "no", "old_price": 0.0006602057258991562, "price_change": 0.9548300788412891}, "27911": {"name": "Sonic", "symbol": "HOTDOG", "date_added": "2023-08-23T21:36:20.000Z", "market_cap": 0, "volume": 953413.07886598, "price": 0.014650033038552637, "volume_converted": "953.0K", "days_passed": 12, "hot": "no", "old_price": 0.014599990549401306, "price_change": 1.0034275699687616}, "27905": {"name": "Baby Shiba Inu", "symbol": "BABYSHIB", "date_added": "2023-08-23T09:35:14.000Z", "market_cap": 0, "volume": 765413.29528044, "price": 0.008343097505390008, "volume_converted": "765.0K", "days_passed": 12, "hot": "no", "old_price": 0.008678341214619228, "price_change": 0.9613700705078893}, "26748": {"name": "Tidalflats", "symbol": "TIDE", "date_added": "2023-09-02T04:45:13.000Z", "market_cap": 0, "volume": 608330.82549439, "price": 0.049647562740725584, "volume_converted": "608.0K", "days_passed": 2, "hot": "yes", "old_price": 0.05029417431234834, "price_change": 0.9871434101371857}, "27853": {"name": "TARALITY", "symbol": "TARAL", "date_added": "2023-08-21T05:43:51.000Z", "market_cap": 0, "volume": 431979.20088399, "price": 0.00121296271650143, "volume_converted": "431.0K", "days_passed": 14, "hot": "no", "old_price": 0.00122264221233698, "price_change": 0.9920831329575572}, "27935": {"name": "PEPECASH", "symbol": "PEPECASH", "date_added": "2023-08-28T09:54:01.000Z", "market_cap": 0, "volume": 398665.02624254, "price": 4.105407951304584e-05, "volume_converted": "398.0K", "days_passed": 7, "hot": "no", "old_price": 4.112739504724884e-05, "price_change": 0.9982173552660272}, "27938": {"name": "Dejitaru Hoshi", "symbol": "HOSHI", "date_added": "2023-08-29T09:03:16.000Z", "market_cap": 0, "volume": 303233.11348277, "price": 0.0030020918416215087, "volume_converted": "303.0K", "days_passed": 6, "hot": "no", "old_price": 0.0029454494157093738, "price_change": 1.0192304867332083}}