{"23149": {"name": "Sei", "symbol": "SEI", "date_added": "2023-08-14T07:35:00.000Z", "market_cap": 229467966.74866387, "volume": 66287078.90625732, "volume_converted": "66.3M", "days_passed": 14, "hot": "no"}, "24781": {"name": "CyberConnect", "symbol": "CYBER", "date_added": "2023-08-15T11:49:15.000Z", "market_cap": 40283986.056003086, "volume": 39350642.12345906, "volume_converted": "39.4M", "days_passed": 13, "hot": "no"}, "27928": {"name": "Pepe Community", "symbol": "PEPE", "date_added": "2023-08-27T03:21:38.000Z", "market_cap": 0, "volume": 28410528.70108403, "volume_converted": "28.4M", "days_passed": 1, "hot": "yes"}, "27922": {"name": "Shiba Saga", "symbol": "SHIA", "date_added": "2023-08-25T03:05:39.000Z", "market_cap": 0, "volume": 17032399.0645706, "volume_converted": "17.0M", "days_passed": 3, "hot": "yes"}, "27864": {"name": "XShiba Inu", "symbol": "XSHIBA", "date_added": "2023-08-17T04:59:26.000Z", "market_cap": 0, "volume": 3655285.45661148, "volume_converted": "3.7M", "days_passed": 11, "hot": "no"}, "27905": {"name": "Baby Shiba Inu", "symbol": "BABYSHIB", "date_added": "2023-08-23T09:35:14.000Z", "market_cap": 0, "volume": 2326773.4270217, "volume_converted": "2.3M", "days_passed": 5, "hot": "no"}, "27852": {"name": "AimBot", "symbol": "AIMBOT", "date_added": "2023-08-16T01:22:45.000Z", "market_cap": 0, "volume": 1961822.66871166, "volume_converted": "2.0M", "days_passed": 12, "hot": "no"}, "27855": {"name": "spurdo", "symbol": "SPURDO", "date_added": "2023-08-16T02:20:11.000Z", "market_cap": 0, "volume": 1945414.2990706, "volume_converted": "1.9M", "days_passed": 12, "hot": "no"}, "27845": {"name": "LINQ", "symbol": "LINQ", "date_added": "2023-08-15T11:56:53.000Z", "market_cap": 0, "volume": 1853039.57258815, "volume_converted": "1.9M", "days_passed": 13, "hot": "no"}, "27867": {"name": "HarryPotterObamaWallStreetBets10Inu", "symbol": "STONKS", "date_added": "2023-08-17T09:54:18.000Z", "market_cap": 0, "volume": 1628016.19790652, "volume_converted": "1.6M", "days_passed": 11, "hot": "no"}, "27901": {"name": "shares.finance", "symbol": "SHARES", "date_added": "2023-08-23T02:42:23.000Z", "market_cap": 0, "volume": 1566764.32160961, "volume_converted": "1.6M", "days_passed": 5, "hot": "no"}, "27911": {"name": "Sonic", "symbol": "HOTDOG", "date_added": "2023-08-23T21:36:20.000Z", "market_cap": 0, "volume": 1161117.26430874, "volume_converted": "1.2M", "days_passed": 5, "hot": "no"}}